telstar/__init__.py
telstar/admin.py
telstar/config.py
telstar/consumer.py
telstar/producer.py
telstar/com/__init__.py
telstar/com/pw.py
telstar/com/sqla.py
telstar/tests/_dbcontent.py
telstar/tests/expected.txt
telstar/tests/peewee_test_consumer.py
telstar/tests/peewee_test_producer.py
telstar/tests/sqlalchemy_test_consumer.py
telstar/tests/sqlalchemy_test_producer.py
telstar/tests/test_telstar.sh
telstar-1.1.3.dist-info/LICENSE
telstar-1.1.3.dist-info/WHEEL
telstar-1.1.3.dist-info/METADATA
telstar-1.1.3.dist-info/RECORD
