Metadata-Version: 2.1
Name: telstar
Version: 1.1.3
Summary: Telstar is a package to write producer and consumers groups against redis streams.
Home-page: https://bitspark.de
License: UNKNOWN
Author: Bitspark
Author-email: kai.koenig@bitspark.de
Requires-Python: >=3.6
Classifier: License :: OSI Approved :: MIT License
Requires-Dist: redis
Requires-Dist: peewee
Requires-Dist: marshmallow
Requires-Dist: SQLAlchemy ; extra == "sqlalchemy"
Provides-Extra: sqlalchemy
